nanopb/__init__.py
nanopb/generator/__init__.py
nanopb/generator/nanopb_generator
nanopb/generator/nanopb_generator.bat
nanopb/generator/nanopb_generator.py
nanopb/generator/nanopb_generator.py2
nanopb/generator/platformio_generator.py
nanopb/generator/proto/Makefile
nanopb/generator/proto/__init__.py
nanopb/generator/proto/_utils.py
nanopb/generator/proto/google/protobuf/descriptor.proto
nanopb/generator/proto/nanopb.proto
nanopb/generator/proto/nanopb_pb2.py
nanopb/generator/protoc
nanopb/generator/protoc-gen-nanopb
nanopb/generator/protoc-gen-nanopb-py2
nanopb/generator/protoc-gen-nanopb.bat
nanopb/generator/protoc.bat
nanopb-0.4.9.dist-info/METADATA
nanopb-0.4.9.dist-info/WHEEL
nanopb-0.4.9.dist-info/entry_points.txt
nanopb-0.4.9.dist-info/RECORD
