Metadata-Version: 2.1
Name: nanopb
Version: 0.4.9
Summary: Nanopb is a small code-size Protocol Buffers implementation in ansi C. It is especially suitable for use in microcontrollers, but fits any memory restricted system.
Home-page: https://jpa.kapsi.fi/nanopb/
License: Zlib
Keywords: protobuf,protoc
Author: Petteri Aimonen
Author-email: jpa@npb.mail.kapsi.fi
Requires-Python: >=2.7
Classifier: License :: OSI Approved
Classifier: Programming Language :: Python :: 2
Classifier: Programming Language :: Python :: 2.7
Classifier: Programming Language :: Python :: 3
Classifier: Programming Language :: Python :: 3.4
Classifier: Programming Language :: Python :: 3.5
Classifier: Programming Language :: Python :: 3.6
Classifier: Programming Language :: Python :: 3.7
Classifier: Programming Language :: Python :: 3.8
Classifier: Programming Language :: Python :: 3.9
Classifier: Programming Language :: Python :: 3.10
Classifier: Programming Language :: Python :: 3.11
Classifier: Programming Language :: Python :: 3.12
Classifier: Topic :: Software Development :: Build Tools
Provides-Extra: grpcio-tools
Requires-Dist: grpcio-tools (>=1.46.0) ; extra == "grpcio-tools"
Requires-Dist: protobuf (>=3.19)
Project-URL: Documentation, https://jpa.kapsi.fi/nanopb/docs/index.html
Project-URL: Repository, https://github.com/nanopb/nanopb/
